{
  "url": "https://news.zhibo8.com/zuqiu/2024-01-06/659939cbee969native.htm",
  "标题": "杜兆才你XX随的什么波逐的什么流，从来没有什么身不由己的鬼话",
  "日期": "2024-01-06",
  "正文": " 身为足协领导，上任时候哪个不是踌躇满志，意气风发。足球尤其是职业足球，剑戟森森，深不可测。杜兆才说的“随波逐流”，反映了这个行业世风日下的现状。足协是行业管理单位，你是掌舵人，行风治理是你的本职，波涛激流是你要斗争的对象，你tm随的什么波，逐的什么流。 从来没有什么身不由己的鬼话。在各种利益诱惑面前，如何保持政治定力，保持一颗对足球事业的热忱之心，取决于你是不是真的爱这项事业，不求回报，不求名利，甘愿奉献，为足球燃烧自己的生命，真正把中国足球振兴当成自己义不容辞的责任。",
  "缩略图": "//tu.duoduocdn.com/uploads/day_240106/202401061931036419.jpg",
  "正文中的图片": [
    "//tu.duoduocdn.com/uploads/day_240106/202401061931036419.jpg"
  ]
}