{
  "url": "https://news.zhibo8.com/zuqiu/2024-01-10/659e25f40b20enative.htm",
  "标题": "巴萨传奇队重返中国，1月20日在重庆vs卡纳瓦罗领衔的IFDA明星队",
  "日期": "2024-01-10",
  "正文": "继在吉尔吉斯斯坦、以色列和刚果民主共和国的比赛之后， 巴萨传奇队将于当地时间1月20日晚上7时重返中国，在山城重庆龙兴足球场对阵IFDA全明星队。 教练阿尔伯特-\"查皮\"-费雷尔将带领強大阵容包括卡莱斯-普约尔、里瓦尔多、哈维尔-萨维奥拉和盖兹卡-门迭塔等球员，迎战由弗朗切斯科-托蒂、费尔南多-莫伦特斯、克拉伦斯-西多夫和法比奥-卡纳瓦罗领衔的IFDA全明星队，其余球员名单将于稍后公布。 重返中国 2010 年夏天，瓜迪奥拉执教的巴萨凭借塞尔吉-罗贝托、诺利托和兹拉坦-伊布拉希莫维奇的进球，以 3:0 击败北京国安足球队。 ",
  "缩略图": "//tu.duoduocdn.com/uploads/day_190419/5cb8ec64ae8c2.jpg",
  "正文中的图片": [
    "//tu.duoduocdn.com/uploads/day_190419/5cb8ec64ae8c2.jpg"
  ]
}