{
  "url": "https://news.zhibo8.com/zuqiu/2024-01-07/65997c0570543native.htm",
  "标题": "邮报独家：难以适应沙特生活，亨德森渴望重返英超踢球",
  "日期": "2024-01-07",
  "正文": " 直播吧1月7日讯据《每日邮报》报道，前利物浦队长亨德森渴望重返英超。如果这笔令人震惊的交易能够成行，这意味着他将损失数百万镑税款和薪水。在达曼协作，亨德森的周薪达到了70万镑。 去年夏天，亨德森以1200万镑的转会费加盟达曼协作，但英格兰中场很难适应那里的生活。这个月，他会认真考虑俱乐部收到的任何报价。达曼协作糟糕的状态加剧了亨德森所面对的问题。去年11月以来，球队已经有8场比赛没有赢球，主教练杰拉德处在了巨大的压力之下。 除了要适应不同的生活方式，33岁的亨德森还需要适应湿热的比赛条件。达曼协作的主场可以容纳35000名球迷，但平均上座人数仅有7800人，这样的上座率并不能鼓舞人心。 （二怪）",
  "缩略图": "//tu.duoduocdn.com/uploads/day_230918/650843452ff5f_watermark.jpg",
  "正文中的图片": [
    "//tu.duoduocdn.com/uploads/day_230918/650843452ff5f_watermark.jpg"
  ]
}