{
  "url": "https://news.zhibo8.com/zuqiu/2024-01-05/6597c5a262381native.htm",
  "标题": "能实现吗❓克林斯曼曾表示，韩国目标亚洲杯夺冠&26年世界杯进4强",
  "日期": "2024-01-05",
  "正文": " 直播吧01月05日讯 据韩媒Star News报道，巴黎球星李刚仁已经与韩国队会合，同时该媒体还回顾主帅克林斯曼在上任时的目标。 克林斯曼曾表示：“赢得亚洲杯是我执教国家队后的第一个目标。”同时终极目标是打进2026年美加墨世界杯四强，重现02年韩日世界杯的辉煌。克林斯曼表示：“韩国队有进入半决赛的经验，我们会给予队员们目标以及信心，我们希望晋级美加墨世界杯半决赛。” 同时该媒体还表示，韩国队目前已经进入黄金一代，每个位置都有亚洲顶尖球员，包括孙兴慜、金玟哉、李刚仁、黄喜灿等等球员。",
  "缩略图": "//tu.duoduocdn.com/uploads/day_231210/65758408bb82c_watermark.jpg",
  "正文中的图片": [
    "//tu.duoduocdn.com/uploads/day_231210/65758408bb82c_watermark.jpg"
  ]
}