{
  "url": "https://news.zhibo8.com/zuqiu/2024-01-11/659f41b78b6b1native.htm",
  "标题": "图片报：拜仁vs霍芬海姆比赛将以多种方式悼念贝肯鲍尔",
  "日期": "2024-01-11",
  "正文": " 直播吧1月11日讯 北京时间1月13日凌晨，拜仁将在德甲第17轮比赛中主场对阵霍芬海姆，据德国媒体《图片报》透露，拜仁将在此役以多种方式悼念去世的贝肯鲍尔。 拜仁纪念贝肯鲍尔 比赛期间，安联球场将亮起“谢谢你，弗朗茨”字样的灯光 球员将佩戴黑色臂章 比赛前除了一分钟的默哀，屏幕上还将回顾贝肯鲍尔的生活场景，并播放他在1966年演唱的歌曲《Gute Freunde》 LED板上将显示“弗朗茨”字样和图片 整个球场将为球迷提供吊唁簿，球迷可以在上面写下对贝肯鲍尔最后的祝愿 （木子）",
  "缩略图": "https://tu.duoduocdn.com/uploads/day_240109/202401090053208297.jpg",
  "正文中的图片": [
    "https://tu.duoduocdn.com/uploads/day_240109/202401090053208297.jpg"
  ]
}