{
  "url": "https://news.zhibo8.com/zuqiu/2024-01-05/6597c5b84a2a5native.htm",
  "标题": "业余和职业差距有多大？于海小学时曾虐了18岁的韩寒20-0",
  "日期": "2024-01-05",
  "正文": " 直播吧1月5日讯 今天，36岁的老将于海宣布退役。在2018年初，于海还以一种意想不到的方式出现在了中国文坛。 2018年初，韩寒写下了一篇文章《我也曾对那种力量一无所知》，谈到了是业余足球和职业足球之间的差距。当时韩寒该文中关于足球的部分如下： 经常有朋友问我，民间高手和职业运动员到底哪个厉害。作为某些运动的民间高手，又作为赛车职业运动员，我更能说说自己的感受。 首先向大家介绍一下我的爱好之一，足球。 足球我自认为脚法不错且身法灵活，从初中开始，班级联赛拿过全校冠军，在校队踢过前锋和门将，新民晚报杯中学生足球赛拿过区的四强，我护球很像梅西，射门很像贝利，曾经一度觉得可以去踢职业试试。然而这一切都在某个下午幻灭了。 那是十几年前，我二十岁，正值当打之年，一个学生网站组织了一场慈善球赛，我和几个球友应邀参加，他们也都是上海高中各个校队的优秀球员。对手是上海一支职业球队的儿童预备队，都是五年级左右的学生。 我们上海高中名校联队去的时候欢声笑语，都彼此告诫要对小学生下手轻一点，毕竟人家是儿童哈哈哈哈。由于匆匆成军，彼此都记不得名字，决定各喊球场上的外号，比如二中菲戈，附中克林斯曼，杨浦范巴斯滕，静安巴乔。 上半场结束后，我作为金山区齐达内只触球了一次。你们没看错，我他妈只触到了球一次，上半场20分钟，我们就被灌了将近20个球。后来裁判嫌麻烦，连进球后半场开球都取消了，直接改为门将发球门球。我们进球0个，传球成功不到十次，其他时间都在被小学生们当狗遛。 半场结束，我们不好意思再称呼对方的外号，改为了叫球衣数字。队长把我们聚在一起，说，兄弟们，这样下去要输50个球，要不下半场我们就都站在门口堵门吧，力保丢30个球以内。 最后这场比赛没有下半场，对方教练终止了比赛，说不能和这样的对手踢球，会影响小队员们的心智健康。于是活动直接进入到慈善捐款环节。我们上海高中联队的球员们在全场女生复杂的眼神中，排队上台，向捐款箱中火速塞钱，并在一片鸦雀无声中退场。 从那次以后，每次和大家一起看球，看到职业队踢了一场臭球以后，身边的朋友们纷纷骂说自己公司的球队上去也能把申花or上港or国安or恒大or国家队等队伍灭掉的时候，我总是笑而不语，心中荡漾起二十岁那个下午，被小学生支配的恐惧。而我也曾对那种力量，一无所知。 ———————————————— 后来，韩寒还在社媒发布了一组当年留下的照片，在韩寒的小学生对手的合影里头，年幼的于海便出现在了前排的C位。随后于海本人确认：“图二第一排中间那位是我没错，当年我们是一支业余俱乐部球队，图中的队友们现在都是上海各行业的精英，偶尔还会聚在一起踢球。欢迎韩导再来切磋！” 韩寒看到于海的转发评论后也表示：“原来18岁那年是被国脚虐了0-20，我内心终于得到了释怀。君子报仇，二十年不晚，我这些年苦练球技，就为了今天能甩下这句话：于海兄，我们赛车场见。” （德里森）",
  "缩略图": "//tu.duoduocdn.com/uploads/news/day_240105/202401051701596885.jpg",
  "正文中的图片": [
    "//tu.duoduocdn.com/uploads/news/day_240105/202401051701596885.jpg"
  ]
}