{
  "url": "https://news.zhibo8.com/zuqiu/2024-01-07/6599f73dcf6a6native.htm",
  "标题": "平托谈自己的未来：每个人都想去英超，那是世界上最好的联赛",
  "日期": "2024-01-07",
  "正文": " 直播吧1月7日讯 罗马总经理平托已经确定将在2月3日离任，而他在接受采访时谈到了自己的未来。 有传闻称平托在离开罗马后可能去英超任职，也有报道称沙特利雅得胜利俱乐部对平托感兴趣。对此平托表示：“英超？这是每个人都想去的联赛，包括球员、教练、管理人员。那是世界上最好的联赛，我迟早都想有英超工作的经历。在结束罗马的工作后，我已经做好了一切准备。” （苏二胡）",
  "缩略图": "//tu.duoduocdn.com/uploads/day_220526/628ea5acedb64_watermark.jpg",
  "正文中的图片": [
    "//tu.duoduocdn.com/uploads/day_220526/628ea5acedb64_watermark.jpg"
  ]
}