{
  "url": "https://news.zhibo8.com/zuqiu/2024-01-02/6592e4bea60f5native.htm",
  "标题": "乌尔赖希：想为拜仁出场达到100次 位置竞争让诺伊尔达到最佳状态",
  "日期": "2024-01-02",
  "正文": " 直播吧1月2日讯   拜仁门将乌尔赖希接受采访谈到了俱乐部的情况。 为拜仁出场98次 我真的很自豪。我希望我能再踢几场比赛，这样我就能达到100场。 在11月的年度股东大会上，会员们为您热烈鼓掌 我当然很高兴会员们感谢我为俱乐部所做的一切。所以这对我来说很重要。我一直都说拜仁是我的家人。 关于比赛 我想获得经验，帮助我进步，为我打开新的大门。但从那以后，一切都以某种方式发展，我一次又一次地延长了合同。我经常参加比赛，在这里我总能感受到大家对我的信任。随着时间的推移，球队、俱乐部、环境和一切都让我喜欢上了。我认为能够在这里担任二号门将是一种荣幸。 花了多长时间才适应做二号门将并接受这个角色？ 当拜仁想把我从斯图加特带回来的时候，我首先想到的是，哇，太酷了，拜仁！但是，下一刻，我意识到，第二门将？我当时26岁，这不在我的职业规划中。但经过几个晚上的思考，我认为这份工作是一个让我进步的好机会。我每天都能从与诺伊尔和这支世界级的球队一起工作中学到很多东西。我意识到有些人可能不理解这一点。但对我来说，这是向前迈出的一步。 位置竞争 竞争是工作的一部分，要想在体育界走得更远，竞争是必不可少的。但知道自己在团队中的位置也很重要。我们有明确的制度，诺伊尔是头号门将。但他知道他必须在每次训练中都全力以赴，因为佩雷茨和我都在挑战他。他也需要这样才能达到他的最高水平。诺伊尔和我之间的关系不仅仅是同事关系。在我们共同生活的许多年里，我们成为了朋友。这对我来说也很重要，因为我必须感觉良好才能去比赛。 当你如此投入比赛，当事情进展顺利时，一开始坐在替补席上显然不容易。但我知道我在拜仁的工作是什么，诺伊尔回来的时候我真的很高兴。我一直都知道我会在训练中帮助他有一个好的复出，我们是一个团队。 （eagle）",
  "缩略图": "//tu.duoduocdn.com/uploads/day_200120/373258359137632266.jpg",
  "正文中的图片": [
    "//tu.duoduocdn.com/uploads/day_200120/373258359137632266.jpg"
  ]
}