{
  "url": "https://news.zhibo8.com/zuqiu/2024-01-02/6593ad3e2f5ccnative.htm",
  "标题": "世体：巴萨了解到亚历克斯-加西亚的实际价格远比赫罗纳给出的低",
  "日期": "2024-01-02",
  "正文": " 直播吧1月2日讯 据《世界体育报》报道，赫罗纳非官方给出的亚历克斯-加西亚的解约金金额，与巴萨了解到的不同。 此前消息称，巴萨有意引进赫罗纳中场亚历克斯-加西亚。世体称，虽然赫罗纳没有给出官方数字，但非官方消息称起步价约为2000万欧元，而巴萨方面的消息人士表示，根据他们的了解，实际价格比2000万低得多，尽管没有具体数字，但大约在1200万欧元左右。 去年夏天巴萨从赫罗纳引进罗梅乌时，最初起步价为1000万欧元，后来赫罗纳降至500万欧元，而最终巴萨只付了380万欧元左右，这是罗梅乌解约金的真正金额。 巴萨现在保持着低调，他们承认球队在寻找一名中场，加西亚上赛季和本赛季都在赫罗纳表现出色，但巴萨保证他不会是候选名单中的唯一人选。 一旦巴萨可以确定有多少资金用于冬季引援，德科和哈维就会敲定名单，拉波尔塔现在正在迪拜和其他地方牵线搭桥，尝试为俱乐部带来更多收入。 就目前的情况来说，巴萨更现实的选择是租借一名球员。 （地精杀手）",
  "缩略图": "//tu.duoduocdn.com/uploads/day_231206/656fc5b9be4f9_watermark.jpg",
  "正文中的图片": [
    "//tu.duoduocdn.com/uploads/day_231206/656fc5b9be4f9_watermark.jpg"
  ]
}