{
  "url": "https://news.zhibo8.com/zuqiu/2024-01-04/6595f0d174243native.htm",
  "标题": "踢球者德甲进攻中场评级：维尔茨世界级，穆西亚拉、穆勒国脚级",
  "日期": "2024-01-04",
  "正文": " 直播吧1月4日讯 本赛季德甲赛程已接近半程，今日德媒《踢球者》公布了德甲进攻型中场球员评分，其中维尔茨获评唯一的世界级，哈维-西蒙斯和霍夫曼获评洲际级。 世界级球员 1、维尔茨，勒沃库森 洲际级球员 2、哈维-西蒙斯，RB莱比锡 3、乔纳斯-霍夫曼，勒沃库森 国脚级球员 4、穆西亚拉，拜仁慕尼黑 5、克拉马里奇，霍芬海姆 6、德米洛维奇，奥格斯堡 7、恩佐-米洛，斯图加特 8、鲍姆加特，RB莱比锡 9、托马斯-穆勒，拜仁慕尼黑 10、布兰特，多特蒙德 11、斯万贝里，沃尔夫斯堡 12、查比，法兰克福 13、罗伊斯，多特蒙德 （Jaden）",
  "缩略图": "//tu.duoduocdn.com/uploads/day_240104/202401040725081668.jpg",
  "正文中的图片": [
    "//tu.duoduocdn.com/uploads/day_240104/202401040725081668.jpg"
  ]
}