{
  "url": "https://news.zhibo8.com/zuqiu/2024-01-04/65968de9e1bcdnative.htm",
  "标题": "麦肯尼：回尤文后一切从零开始 未来只想留在尤文&目标赢意甲冠军",
  "日期": "2024-01-04",
  "正文": " 直播吧1月4日讯 接受记者采访时，尤文图斯中场麦肯尼谈到了自己的未来、自己与队友的关系，以及关于尤文图斯的话题。 麦肯尼表示：“回到尤文图斯？当我离开利兹联时，我知道我给人留下了不好的印象，但是在利兹联，我培养了一种心态。当我回到尤文图斯时，我是从零开始的，感觉就像是我刚刚加盟时一样，我知道我必须再次证明我自己。” “我的未来？我只想留在这里，尽可能多地做出贡献，实现我还没有实现的目标，那就是赢得联赛冠军。这是我们所有人都想做的事情，让尤文图斯回到应该在的位置。我希望球队取胜，实现A计划，即拿到欧冠资格，并赢得意甲冠军。” “我与小维阿的关系？有他这样的球员在球队当中总是很棒，因为我们都背井离乡，我们是彼此的‘家人’。我很善于交际，我能与任何球员相处融洽，但是我最喜欢与小基恩和小维阿在一起。” （铁甲钢拳）",
  "缩略图": "//tu.duoduocdn.com/uploads/day_210124/600d7b6ae32ea.jpg",
  "正文中的图片": [
    "//tu.duoduocdn.com/uploads/day_210124/600d7b6ae32ea.jpg"
  ]
}