{
  "url": "https://news.zhibo8.com/zuqiu/2024-01-11/659f37c7b9aa9native.htm",
  "标题": "津媒：中超八队完成主帅更替 新帅会给中超带来新气象",
  "日期": "2024-01-11",
  "正文": " 直播吧1月11日讯 据《今晚报》报道，新赛季还未开始，中超联赛的八支队伍就已完成主帅更替。新教练到来以后，不仅将激活各队沉闷的球风，也会给中超带来新气象。 在海口观澜湖足球训练基地的冬训队伍中，上海申花队备受关注，焦点就在该队刚刚签约的俄罗斯主帅斯卢茨基身上。纵观这几天的训练，他的执教风格已经展现得淋漓尽致，不仅训练强度很大，而且他还要求球员必须要快。在训练中，无论是抢圈热身，还是专项技术练习的分组对抗，斯卢茨基都要求球员尽可能地用一脚或者两脚把球处理掉，不允许拖泥带水、贻误战机情况的出现。 昨天，上海海港队刚刚上任的主教练穆斯卡特正式进入工作模式，这也标志着卫冕冠军新赛季将换一种足球风格。穆斯卡特推崇进攻，喜欢压迫，追求高强度、快节奏的对抗风格。很显然，这和海港队上赛季主帅哈维尔的执教风格截然不同。此外，不同于哈维尔的死活不肯轮换，穆斯卡特在执教日本横滨水手队时坚决轮换策略，用人比较灵活。 附中超教练更换如下： 申花 吴金贵→斯卢茨基 海港 哈维尔→穆斯卡特 河南队 萨尔科→南基一 南通支云 帕特里西奥米→哈洛-尤拉索维奇 梅州客家 米兰-里斯蒂奇→巴勃罗 青岛海牛 安东尼奥→亚森 武汉三镇 高畠勉→罗德里格斯 青岛西海岸 扬戈维奇→黑崎久志 （德里森）",
  "缩略图": "https://tu.duoduocdn.com/uploads/news/day_240108/202401081143075248.jpg",
  "正文中的图片": [
    "https://tu.duoduocdn.com/uploads/news/day_240108/202401081143075248.jpg"
  ]
}