{
  "url": "https://news.zhibo8.com/zuqiu/2024-01-09/659d23335536cnative.htm",
  "标题": "巴萨西超杯大名单：莱万、罗克、佩德里、德容、阿劳霍在列",
  "日期": "2024-01-09",
  "正文": " 直播吧1月9日讯 北京时间1月12日凌晨，巴萨将在西超杯半决赛中对阵奥萨苏纳，巴萨公布了西超杯球员名单，莱万、罗克、佩德里、德容在列。 巴萨西超杯大名单 门将：13-佩尼亚、26-阿斯特拉拉加 后卫：2-坎塞洛、3-巴尔德、4-阿劳霍、5-伊尼戈-马丁内斯、15-克里斯滕森、23-孔德、31-科琛、33-库巴西、39-埃克托-福特 中场：8-佩德里、18-罗梅乌、20-罗贝托、21-德容、22-京多安、30-卡萨多、32-费尔明 前锋：7-费兰-托雷斯、9-莱万、11-拉菲尼亚、14-菲利克斯、19-罗克、27-亚马尔、38-吉乌 注：佩德里、伊尼戈-马丁内斯、坎塞洛随队出征，但能否出场尚未得到医疗团队确认 （木子）",
  "缩略图": "//tu.duoduocdn.com/uploads/news/day_240109/202401091839495976.jpg",
  "正文中的图片": [
    "//tu.duoduocdn.com/uploads/news/day_240109/202401091839495976.jpg"
  ]
}