{
  "url": "https://news.zhibo8.com/zuqiu/2024-01-06/6598ba115c969native.htm",
  "标题": "【投票通知】陕西长安联合俱乐部名称修改",
  "日期": "2024-01-06",
  "正文": " 2024年1月5日，中国足协公布了三级职业联赛首批完成足球行业内债务清欠的俱乐部名单，彬州辉龙（陕西长安联合）在列。陕西长安联合迈出了获得2024赛季职业联赛准入资格的关键一步。 陕西长安联合2023赛季以“彬州辉龙”的名称参加中冠联赛，在进军职业联赛之后，俱乐部一直在积极推进俱乐部名称在官方层面的更改，在《中国足球协会职业俱乐部和球队名称管理规定》发布后，我俱乐部积极响应决策。现因客观因素，以及规避未来可能存在的生存风险。俱乐部决定进行官方名称修改，因俱乐部名称修改为重大决策，根据《会员管理办法（试行版）》，俱乐部将发起「俱乐部名称修改意见投票」。 拟定投票名称为： 1.陕西联合足球俱乐部 2.陕西西北联合足球俱乐部 3.彬州辉龙足球俱乐部 「投票时间」2024年1月6日10:00-2024年1月7日10:00 「投票方式」进入「长安联合会员中心小程序」-「会员投票」-「俱乐部名称修改意见投票」 「投票详情」参议会员、联合会员每人一票，得票数第一位的候选名称即为最终俱乐部官方名称。",
  "缩略图": "//tu.duoduocdn.com/uploads/day_240106/202401061026164563.jpg",
  "正文中的图片": [
    "//tu.duoduocdn.com/uploads/day_240106/202401061026164563.jpg"
  ]
}