{
  "url": "https://news.zhibo8.com/zuqiu/2024-01-05/6597c6f527a51native.htm",
  "标题": "罗马诺：国米中场阿戈梅不会加盟马赛，塞维接触国米租借球员",
  "日期": "2024-01-05",
  "正文": " 直播吧1月5日讯 罗马诺的消息，国米中场阿戈梅加盟马赛的交易告吹，而塞维接触了国米希望能完成这笔交易。 尽管当地时间昨晚，国米马赛接近就阿戈梅达成一致，不过由于球员对最终细节持怀疑态度，也改变了俱乐部的立场，这笔交易告吹。 塞维利亚和国米今天就阿戈梅交易进行了直接谈判，塞维将在租借协议中加入一个选择买断条款。 阿戈梅21岁，本赛季为国米只替补出场1次。 （mageth）",
  "缩略图": "//tu.duoduocdn.com/uploads/news/day_240105/202401051706514578.jpg",
  "正文中的图片": [
    "//tu.duoduocdn.com/uploads/news/day_240105/202401051706514578.jpg"
  ]
}