{
  "url": "https://sports.sina.com.cn/g/laliga/2020-01-05/doc-iihnzhha0382857.shtml",
  "标题": "曾与梅西合影的那个中国男孩 如今让梅西尝到苦涩",
  "日期": "2020年01月05日 07:48",
  "正文": " 加泰罗尼亚德比虽然等级远不如巴萨和皇马的国家德比，但也吸引了不少媒体的关注。这次的加泰德比，西班牙人凭借武磊最后时刻的进球，2比2逼平了强大的巴萨，而阿根廷最大的体育日报《奥莱报》也对此进行了报道，该报打出了“武磊，从2008年的合影到现在让梅西品尝苦涩”的标题，表示这位在最后时刻帮助西班牙人扳平比分的中国前锋，和梅西之间有一段特殊的历史。武磊被认为是中国最好的球员，现在他在另外的赛场也爆发了。 《奥莱报》表示，在对西班牙人的加泰德比中，巴萨品尝了苦涩的味道，因为武磊在比赛时间所剩无几的情况下扳平了比分。那么，这个令所有人都惊讶的中国球员是谁？他有什么样的历史？要讲述他的故事，首先要从2008年北京奥运会说起，在那里，他与梅西有了一张合影，而在12年后，他让梅西在球场上经历了痛苦。 16岁的武磊穿着阿根廷国家队的球衣，与梅西以及阿圭罗合影。现在武磊被视为中国最好的球员，而除了水准，他加盟西班牙人还有商业方面的原因。他在西班牙人的首秀有4000万观众观看，媒体影响力比梅西大14倍，这令人印象深刻。而现在，他又成为了历史上首位攻破巴萨大门的中国球员。12年前，武磊高高兴兴地与梅西合影，12年后，他让梅西和巴萨痛苦。（伊万）",
  "缩略图": "//n.sinaimg.cn/sports/transform/700/w448h252/20200105/232b-imrkkfx8113316.jpg",
  "正文中的图片": [
    "//n.sinaimg.cn/sports/transform/700/w448h252/20200105/232b-imrkkfx8113316.jpg",
    "//n.sinaimg.cn/sports/transform/229/w650h379/20200105/3749-imrkkfx8111213.png"
  ]
}