{
  "url": "https://sports.sina.com.cn/g/laliga/2022-10-17/doc-imqmmthc1207058.shtml",
  "标题": "克罗斯称赞巴尔韦德：这是世界排名前三的球员",
  "日期": "2022年10月17日 19:50",
  "正文": "周日，皇马在国家德比中3比1击败巴萨，赛后克罗斯在社交网站上称赞比赛中打入一球的巴尔韦德是世界排名前三的球员。 巴尔韦德本赛季表现出色，他在对阵巴萨的比赛中取得的进球，是本赛季西甲取得的第4球，此外他在欧冠还有1球，这也是他职业生涯中进球最多的一个赛季。 中场大哥克罗斯赛后用一句简洁的话表扬了这位乌拉圭国脚的实力：“巴尔韦德是在目前排名世界前三。” 巴尔韦德则谈到了他在不同位置的作用：“我试着在每个位置都享受自己，都尝试发挥出最大的作用。我知道如果我在前面，我可以进球和助攻，在中场，我可以贡献我的能量和，努力跑动，当然还有进球，所以我今天很开心。” （塞尔吉奥） ",
  "缩略图": "//n.sinaimg.cn/sports/transform/199/w600h399/20221017/9e87-14d788378c672b2c7660919a03aefcf5.jpg",
  "正文中的图片": [
    "//n.sinaimg.cn/sports/transform/199/w600h399/20221017/9e87-14d788378c672b2c7660919a03aefcf5.jpg"
  ]
}