{
  "url": "https://sports.sina.com.cn/g/pl/2021-05-06/doc-ikmxzfmm0734014.shtml",
  "标题": "经纪人：克洛普绝对忠于利物浦 无欧战他也不会离开安菲尔德",
  "日期": "2021年05月05日 23:46",
  "正文": "尤尔根·克洛普“绝对”忠于利物浦，根据他的经纪人马克·科西克表示，即使俱乐部无法参加下赛季欧战比赛。 红军，上赛季的英超冠军和之前的欧冠之王，本赛季经历了一个艰难的赛季，他们将努力保持前四名的竞争力。 他们目前排在英超第七名，而目前他们还有5场联赛要踢，如果无法在积分榜上再进一步，他们则真的有可能无法进入下赛季的欧战赛场，而根据他们主帅的经纪人的说法，即便没有欧战可踢，这位德国教练也没有要离开安菲尔德的意思。 德国天空体育在周末对阵南安普顿的比赛前被问及这一点，科西克强调，克洛普仍然致力于眼前进入联赛前四名的任务。 “绝对如此！”当被问及这位多特蒙德前主帅是否会留在安菲尔德时，他回答道。 当进一步被追问克洛普是否在他的合同中有解约金条款事，科西克则拒绝讨论任何类似的问题。 以英超冠军的标准来看，利物浦本赛季在积分榜上的下滑令人震惊，红军在卫冕伊始的辉煌表现更反衬了年后的糟糕状态，这可能会让他们本赛季颗粒无收。 尤其是他们在本赛季遭遇了严重的伤病困扰，包括后防核心在内的维吉尔·范戴克在内的诸多后卫球员都不得不因伤缺席了不少的比赛，这让他们在卫冕默西塞德郡三十年来第一个联赛冠军之路变得异常艰难。 克洛普是他当代最受人尊敬的教练之一，他遇到的这些麻烦让他与德国国家队空缺的主帅位置有所联系，现在德国战车掌舵者勒夫将在今夏的欧洲杯比赛过后离任。 科西克再次保证，克洛普将继续专注于自己在安菲尔德的未来，这无疑会安抚那些希望他继续留在安菲尔德的球迷。",
  "缩略图": "未找到图片",
  "正文中的图片": []
}