{
  "url": "https://sports.sina.com.cn/g/euro2020/2021-07-01/doc-ikqciyzk2893012.shtml",
  "标题": "名帅要复出了？荷媒曝范加尔有望第三次执教荷兰队",
  "日期": "2021年07月01日 08:43",
  "正文": "荷兰名帅范加尔可能会第三次执教国家队。[欧洲杯1/4决赛盈利秘籍都在这!][下载APP盈利翻倍!] 来自荷兰媒体的消息称，69岁的范加尔准备再度复出，接替弗里克·德波尔，第三次执教荷兰国家队。 范加尔2016年被曼联解雇，2019年正式宣布退出足坛。不过这位名帅看来并不甘心就此隐退，荷乙一支球队不久前就宣布，范加尔将在一场慈善赛中执教本队。 在欧洲杯1/8决赛中，小组赛3战3胜的荷兰被捷克淘汰，主教练弗兰克·德波尔之后也宣布辞职。荷兰媒体透露，范加尔现在愿意再次执教荷兰。 范加尔曾在2000年和2012年两度接手荷兰队，2014年还率队拿到世界杯季军。去年科曼离开荷兰国家队后，就有消息称范加尔要接手荷兰队。（伊万） ",
  "缩略图": "//n.sinaimg.cn/sports/transform/198/w600h398/20210701/ccc6-krwipas2495153.jpg",
  "正文中的图片": [
    "//n.sinaimg.cn/sports/transform/198/w600h398/20210701/ccc6-krwipas2495153.jpg"
  ]
}