{
  "url": "https://sports.sina.com.cn/g/laliga/2020-07-15/doc-iivhuipn3108871.shtml",
  "标题": "皇马强势崛起6大关键:齐祖完美掌舵 本泽马爆发",
  "日期": "2020年07月15日 11:42",
  "正文": "西甲复赛后皇马表现强劲，一波9连胜让他们逆转巴萨，接近了西甲冠军。下轮西甲，皇马只要获胜就能提前夺冠，而如果巴萨不能获胜，那皇马输球都可以提前捧杯。 皇马的这一波9连胜相当成功，球队打入了17球，只丢掉3球。西甲复赛后，皇马主场3比1击败埃瓦尔，主场3比0胜瓦伦西亚，客场2比1击败皇家社会，主场2比0击败马略卡，客场1比0击败西班牙人，主场1比0击败赫塔菲，客场1比0战胜毕尔巴鄂竞技，主场2比0战胜阿拉维斯，客场2比1拿下格拉纳达，对手中有不少实力强劲的球队。 拉莫斯表示，停赛几个月对皇马十分有利，让球队做好了充分的准备。西班牙《国家报》认为，皇马是以备战世界杯或者欧冠淘汰赛的方式在备战西甲最后11轮，比赛正式开始后，皇马体现出的是整个系统的实力。 而《阿斯报》则指出了皇马西甲复赛后连战连胜的6大关键。首先是球队拥有很高的控球率，西甲复赛后皇马场均控球率达到61%，而一场比赛，皇马只被对手射门3次。 第二，齐达内在西甲复赛后使用了4种战术，一方面让所有球员融入球队，另一方面也让对手猝不及防。第三，齐达内基本上让每位球员都上场，球队本赛季有多达21名球员取得进球，这是西甲的纪录。 第四，库尔图瓦在门前一夫当关万夫莫开，本赛季他18次零封对手，而皇马这赛季只丢掉22球。第五，拉莫斯引领球队后防线表现出色，多名后卫取得进球，拉莫斯自己也打入10球。最后，最好的本泽马也回来了，法国人本赛季西甲已经打入了19球，多次打入关键进球。（塞尔吉奥）",
  "缩略图": "//n.sinaimg.cn/sports/transform/706/w650h856/20200715/f619-iwhseiu6167214.jpg",
  "正文中的图片": [
    "//n.sinaimg.cn/sports/transform/706/w650h856/20200715/f619-iwhseiu6167214.jpg"
  ]
}