{
  "url": "https://sports.sina.com.cn/g/euro2020/2021-06-28/doc-ikqcfnca3622493.shtml",
  "标题": "耻辱出局！荷兰全场0射正史上最差 德波尔该背锅吗？",
  "日期": "2021年06月28日 02:46",
  "正文": "北京时间6月28日凌晨，欧洲杯1/8决赛第二个比赛日，十人荷兰0-2不敌捷克，惨遭淘汰。德波尔的球队小组赛3战全胜，进8球仅丢2球，头名出线，但现在却遗憾止步16强。[欧洲杯盈利秘籍都在这!][下载APP盈利翻倍!] 本场比赛，两队上半场0-0战平，但下半时开场不久后风云突变，先是马伦错失绝佳单刀，4分钟后德里赫特手球被直红罚下；少打一人的荷兰在随后的比赛中连丢两球，无力回天。 此役，荷兰全场竟然没有一脚射正，实在是让人大跌眼镜；这也是自1980年国际大赛有数据记录以来，橙衣军团首次在大赛中单场0射正。 值得一提的是，不算点球大战的话，荷兰队近5场欧洲杯淘汰赛一场都没赢过，他们上一次做到还要追溯到2000年欧洲杯，当时在1/4决赛上6-1大胜南斯拉夫。 （七七） ",
  "缩略图": "//n.sinaimg.cn/sports/transform/283/w650h433/20210628/d78f-krwipar8150093.jpg",
  "正文中的图片": [
    "//n.sinaimg.cn/sports/transform/283/w650h433/20210628/d78f-krwipar8150093.jpg"
  ]
}