{
  "url": "https://sports.sina.com.cn/g/pl/2020-09-16/doc-iivhuipp4674745.shtml",
  "标题": "定了！热刺签皇马名将达协议 转会费3000万欧",
  "日期": "2020年09月16日 15:16",
  "正文": "热刺和皇马球员雷吉隆传出绯闻，这笔交易进展很快，如今各方已经达成了协议，只剩下官宣。 名记罗马诺发布最新消息称，雷吉隆要去热刺了，在过去几个小时里，皇马和热刺达成了协议，雷吉隆将以3000万欧元的转会费加盟热刺（约合2755万英镑）。 与此同时，热刺也和雷吉隆达成了个人协议，如今这笔交易只剩下了官宣。 雷吉隆现年23岁，司职左后卫，上个赛季他被租借至塞维利亚，随队拿到了欧联杯冠军。目前皇马主帅齐达内更信任门迪和马塞洛，因此雷吉隆在皇马并没有机会，离队成为了他的选择。 （小九）",
  "缩略图": "//n.sinaimg.cn/sports/transform/215/w650h365/20200916/5d32-izeysaz4917053.jpg",
  "正文中的图片": [
    "//n.sinaimg.cn/sports/transform/215/w650h365/20200916/5d32-izeysaz4917053.jpg"
  ]
}