{
  "url": "http://sports.sina.com.cn/g/pl/2018-12-02/doc-ihpevhcm7203430.shtml",
  "标题": "英超-卢卡库破荒拉什福德2助攻 曼联连扳2球2-2平",
  "日期": "2018年12月02日 03:23",
  "正文": "北京时间12月2日01：30（英国当地时间1日17：30），2018/19赛季英超第14轮一场焦点战在圣玛丽球场展开争夺，曼联客场2比2战平南安普敦，阿姆斯特朗和塞德里克进球，卢卡库和埃雷拉连入2球扳平，拉什福德贡献2助攻。 曼联近19战南安普敦仅负2场，其余17场取得14胜3平。双方英超历史交锋38场，曼联25胜6平7负占据上风，其中客场11胜3平5负。这是双方历史上第124场交锋，此前曼联64胜32平27负占据上风。卢卡库和博格巴回到首发，阿什利-扬、麦克托米奈和埃雷拉轮换出场，马蒂奇回撤客串中卫。 第3分钟，麦卡锡大脚开球踢空，拉什福德小禁区左侧底线上脚后跟回传，吉田麻也小禁区前解围被埃雷拉挡下，卢卡库12码处射门被麦卡锡扑出。南安普敦打出反击，但雷蒙德禁区前低射偏出。阿什利-扬禁区右侧射门被封堵，奥巴费米禁区边缘内射门被马蒂奇挡出。 南安普敦第13分钟取得领先，奥巴费米传球，无人防守的阿姆斯特朗禁区右侧12码处劲射远角入网。 南安普敦第20分钟扩大比分，塞德里克20码处任意球直接射入左上角，2-0。阿什利-扬开出角球，麦克托米奈近距离头球攻门偏出。卢卡库传球，拉什福德外围射门偏出。 曼联第33分钟扳回一城，博格巴直传，拉什福德突破传球，跟进的卢卡库11码处单刀推射入网，1-2。这是比利时人近12场比赛的首粒入球。 曼联第39分钟扳平，拉什福德禁区右侧下底传中，埃雷拉前点近距离脚后跟射门被扑挡后入网，2-2。 曼联下半场加强攻势。阿什利-扬右路任意球传中，费莱尼头球攻门偏出。雷蒙德右路任意球直接射门被德赫亚没收。阿姆斯特朗传球，加比亚迪尼禁区左侧20码处劲射被没收。马蒂奇传球，博格巴15码处倒钩射门也被没收。达洛特替换受伤的卢克-肖出场。 南安普敦利用反击牵扯曼联的进攻。史蒂芬斯传球，雷蒙德禁区边缘内切后射门打飞。赫伊别尔远射被没收。马夏尔替换拉什福德出场。博格巴后场丢球，勒米纳传球，雷蒙德30码外远射被德赫亚托出横梁，赫伊别尔角球混战中头球攻门偏出。伤停补时，加比亚迪尼右路任意球直接射门高出。 南安普敦(3-5-1-1)：1-麦卡锡；3-吉田麻也，4-韦斯特加德，5-史蒂芬斯；43-瓦莱里，23-赫伊别尔，18-勒米纳，17-阿姆斯特朗，2-塞德里克；22-雷蒙德；61-奥巴费米(64',20-加比亚迪尼) 曼联(4-4-2)：1-德赫亚；18-阿什利-扬，31-马蒂奇，4-琼斯，23-卢克-肖(72',20-达洛特)；27-费莱尼，39-麦克托米奈，21-埃雷拉，6-博格巴；9-卢卡库(86',14-林加德)，10-拉什福德(77',11-马夏尔) 水晶宫主场2比0取胜伯恩利。第16分钟，汤森德传球，麦克阿瑟右路传中，迈尔小禁区边缘抢点射门踢漏，皮球弹地后跃入远角。第77分钟，库亚特长传，汤森德右路内切至禁区前劲射远角入网。 布莱顿客场2比1取胜哈德斯菲尔德。开场仅55分钟，布鲁诺禁区右侧草率大脚解围吊向小禁区边缘，赞卡头球攻门击中左侧立柱内侧入网。第32分钟，哈德斯菲尔德中场穆尼耶踢中比苏马小腿被红牌直接罚下。布莱顿连入2球反超，半场补时，马奇右路战术角球传中，达菲小禁区前强力冲顶破门。第69分钟，马奇右路传中，安多内前点小禁区前顶入近角。 莱斯特城主场2比0力克沃特福德。第12分钟，瓦尔迪禁区左侧被福斯特出击扑倒，瓦尔迪亲自主罚点球命中。第23分钟，阿尔布莱顿右路斜传，麦迪逊1打3强突禁区边缘内抽射右下角入网。第90分钟，卡普埃双腿踩踏伊赫纳乔被红牌罚下。 西汉姆客场3比0完胜纽卡斯尔。第11分钟，斯诺德格拉斯右路传中，无人防守的埃尔南德斯小禁区边缘推射入网。第63分钟，阿瑙托维奇头球摆渡，埃尔南德斯禁区右侧单刀低射近角入网。第93分钟，威尔希尔传球，安德森突入禁区左侧10码处单刀低射破门。 (斯科)",
  "缩略图": "//n.sinaimg.cn/sports/transform/286/w650h436/20181202/iYan-hpinryc0133989.jpg",
  "正文中的图片": [
    "//n.sinaimg.cn/sports/transform/286/w650h436/20181202/iYan-hpinryc0133989.jpg",
    "//n.sinaimg.cn/sports/transform/283/w650h433/20181202/-BUN-hpinryc0129590.jpg",
    "//n.sinaimg.cn/sports/transform/429/w274h155/20181202/9LaD-hpevhcm7243669.gif",
    "//n.sinaimg.cn/sports/transform/429/w274h155/20181202/libW-hpfycet0067336.gif",
    "//n.sinaimg.cn/sports/transform/429/w274h155/20181202/0-Rq-hpevhcm7244027.gif",
    "//n.sinaimg.cn/sports/transform/429/w274h155/20181202/3ilk-hpinryc0161258.gif",
    "//n.sinaimg.cn/sports/transform/267/w650h417/20181202/SU7r-hpfycet0034992.jpg",
    "//n.sinaimg.cn/sports/transform/343/w650h493/20181202/O9fM-hpfycet0067808.jpg",
    "//n.sinaimg.cn/sports/transform/239/w650h389/20181202/c_Z--hphsupx7961043.jpg",
    "//n.sinaimg.cn/sports/transform/343/w650h493/20181202/JR8--hpevhcm7244072.jpg",
    "//n.sinaimg.cn/sports/transform/378/w650h528/20181202/lgIe-hpfycet0067489.jpg"
  ]
}