{
  "url": "https://sports.sina.com.cn/global/others/2023-07-26/doc-imzcymix7199558.shtml",
  "标题": "梅西美职联第二场首发担任队长 梅西两场比赛进三球",
  "日期": "2023年07月26日 08:34",
  "正文": " 北京时间7月26日，北美联赛杯的一场较量，迈阿密国际主场迎战亚特兰大联。赛前，两支球队公布了首发阵容，迈阿密国际方面，梅西和布斯克茨均首发出战，目前，梅西梅开二度，泰勒凌空抽射破门，迈阿密国际3比0领先亚特兰大。 迈阿密国际首发：1-卡伦德、32-艾伦、31-米勒、27-克里夫佐夫、2-耶德林、3-阿罗约、16-泰勒、30-克雷马奇、5-布斯克茨、10-梅西、17-马丁内斯 迈阿密国际替补：29-多斯桑托斯、99-詹森、28-阿斯科纳、49-博尔盖林、9-坎帕纳、4-麦克维伊、20-哈维-内维尔、19-罗宾逊、41-大卫-鲁伊斯、15-塞勒、13-乌略亚 亚特兰大联首发：1-古赞、4-艾布拉姆、22-胡安-桑切斯、12-罗宾逊、11-伦农、5-索萨、20-罗塞托、26-威利、23-阿尔马达、28-沃尔夫、7-亚库马基斯 亚特兰大联替补：25-迪奥普、31-韦斯特伯格、13-塞迪奇、37-麦克法登、2-埃尔南德斯、19-贝瑞、24-科布、6-阿隆索、8-穆扬巴、18-艾蒂安、35-福琼、21-莫斯克拉 （佟恒） ",
  "缩略图": "//k.sinaimg.cn/n/sports/transform/216/w650h366/20230726/9718-7652175eddd82fad9fa23d505b274c80.png/w700d1q75cms.jpg?by=cms_fixed_width",
  "正文中的图片": [
    "//k.sinaimg.cn/n/sports/transform/216/w650h366/20230726/9718-7652175eddd82fad9fa23d505b274c80.png/w700d1q75cms.jpg?by=cms_fixed_width"
  ]
}