{
  "url": "https://sports.sina.com.cn/g/laliga/2020-02-02/doc-iimxyqvy9601052.shtml",
  "标题": "齐达内牛！半场连换2人扭转比赛 这就是他的玄学",
  "日期": "2020年02月02日 02:19",
  "正文": "又是一场马德里德比，最终皇马在伯纳乌笑到了最后，凭借本泽马的进球，皇马1-0击败马竞，继续领跑西甲积分榜。 此前西班牙超级杯决赛，齐达内祭出五中场的战术，最终点球击败马竞，而这一次再战马竞，齐达内依然祭出五种场战术，后场不变，前场只是用本泽马顶替了约维奇。但是这一次遭到了挫折，整个上半场，马竞机会更多，踢得更加主动，多次获得射门良机，但均未能把握。 中场休息，齐达内安排巴斯克斯、维尼休斯两名球员热身，下半场刚开始果断换人，换上巴斯克斯、维尼休斯，换下克罗斯、伊斯科。中场休息连换两人，齐达内魄力不小！ 齐达内换上两名边锋，改打433，驳回了他上半场的451战术。这次变阵也是立竿见影，皇马利用边路风生水起，本泽马也活跃了，最终在第56分钟，皇马打破僵局，维尼休斯妙传，门迪杀入禁区传中，本泽马抢点推射破门得分。 皇马下半场也是焕然一新，几乎压制了马竞，无论是射门还是射正，都是全面压制。马竞下半场都没能威胁库尔图瓦。 （Tony）",
  "缩略图": "//n.sinaimg.cn/sports/transform/282/w650h432/20200202/dd4b-intiarq0993537.jpg",
  "正文中的图片": [
    "//n.sinaimg.cn/sports/transform/282/w650h432/20200202/dd4b-intiarq0993537.jpg"
  ]
}