{
  "url": "https://sports.sina.com.cn/china/2023-07-24/doc-imzctxcz9146362.shtml",
  "标题": "沈阳城市领队掌掴主裁 俱乐部:已道歉将内部整改",
  "日期": "2023年07月24日 08:51",
  "正文": "来源：张逸飞/新华社 新华社沈阳7月23日消息，在23日进行的中甲联赛第15轮南京城市主场迎战辽宁沈阳城市的比赛中，客队领队段鑫对当值主裁判不满，被出示红牌后突然掌掴对方。但随后俱乐部官方声明称，段鑫及一线队管理人员已就不理智行为进行诚挚道歉，俱乐部将对球队存在问题进行内部整改。 该事件发生在上半场补时阶段，当时沈阳城市以0：1落后。由于段鑫对主裁判陈浩的判罚不满，陈浩向其出示红牌，在亮牌过程中被段鑫伸手一掌打在脸上。其他人员见状立刻将两人隔开，避免了冲突进一步升级。 掌掴主裁后不久，段鑫抱头晕倒，并被送上开进场内的救护车。重新恢复比赛后，双方球员再次爆发肢体冲突。上半场结束前，沈阳城市的姜峰也被红牌罚下，最终10人应战的沈阳城市以0：4负于南京城市。 当日23时03分，辽宁沈阳城市足球俱乐部发布公告称，俱乐部领队段鑫对裁判判罚有异议，出现了不理智举动，违反了中国足协联赛纪律准则，赛后俱乐部管理层已经与段鑫进行了沟通。“段鑫以及一线队管理人员认识到错误的严重性，也第一时间找到比赛监督和当值裁判，就不理智行为进行诚挚道歉。在一线队从客场返回沈阳后，俱乐部将根据国家体育总局最新行业整顿要求，对球队存在问题进行内部整改。” 2015年，时任原山东鲁能主教练库卡曾因“在球员通道内参与殴打第一助理裁判”被禁赛7个月。",
  "缩略图": "//n.sinaimg.cn/sports/transform/166/w571h395/20230724/d8c4-gifedc6880cf2d94d0906e064cd85d31fa0.gif",
  "正文中的图片": [
    "//n.sinaimg.cn/sports/transform/166/w571h395/20230724/d8c4-gifedc6880cf2d94d0906e064cd85d31fa0.gif",
    "//k.sinaimg.cn/n/sports/transform/226/w603h423/20230724/7514-867d9fe684cc992165b7491b88206b58.jpg/w700d1q75cms.jpg?by=cms_fixed_width"
  ]
}