{
  "url": "http://sports.sina.com.cn/g/pl/2018-01-01/doc-ifyqcwaq6475154.shtml",
  "标题": "曼城有个超级终结者！瓜帅这5000万花的真不贵",
  "日期": "2018年01月01日 00:12",
  "正文": "和水晶宫的比赛，曼城球员给人的整体印象只能用两个字形容——累了。德布劳内和费尔南迪尼奥传球出现失误，萨内在边路冲不起来，斯特林的带球磕磕绊绊……而正是在曼城多名球员疲惫乏力的衬托下，沃克尔的表现让人眼前一亮。 上半场比赛曼城在场面上还能形成压制，水晶宫也不敢贸然大举进攻，到了下半场，蓝月军团体力下降明显，占据主场优势的水晶宫开始对曼城的防线展开冲击，这个时候，沃克尔的作用就体现出来了。第53分钟，扎哈在反击中想硬吃沃克尔，反被后者牢牢地占住身位，扎哈无奈之下将球带出了边线；3分钟后，扎哈故技重施，又被沃克尔防住。 沃克尔最劲爆的表现还是在比赛的最后阶段。第83分钟，扎哈想用速度突破沃克尔，沃克尔回追也不慢，在身体的比拼中，双方上肢接触，沃克尔手一伸，扎哈就像碰到了一堵墙一般，倒在地上，双方机会五五开，裁判没有吹犯规，沃克尔防守成功；4分钟后，本特克在边线处跳起争球，沃克尔上前轻轻一靠，直接把本特克撞趴到场边。 扎哈和本特克，在英超也是成名已久的妖锋，扎哈脚下技术出色，速度快，身体也硬朗。本特克更不必说了，标准的黑又硬前锋。没想到这两人在沃克尔面前，都占不到任何便宜。下半场扎哈在左路屡次想突破，都被沃克尔防得很狼狈，一度被逼得跑到右路寻找机会。而本特克在被沃克尔撞到场边后露出迷惑的眼神，仿佛在问沃克尔：哥们儿，你怎么还不累？ 的确，沃克尔的体能十分惊人。在曼城队内，除了埃德森，沃克尔的出勤率排在德布劳内、奥塔门迪和费尔南迪尼奥之后，算是出勤率极高的球员了。考虑到他踢的是右边后卫的位置，助攻的时候要跑上去，防守的时候还要跑回来，上下往返跑的频率还在这几人之上，如此充沛的体能，真的是让人叹为观止。 联赛已经过半，曼城进入了赛季四线作战的关键时刻，英超的圣诞魔鬼赛程让各大豪门都有些吃力。即使是连胜18场的曼城，终于也显露出疲态。不过，沃克尔镇守的右路至少可以让瓜迪奥拉放心。5000万镑买到这样的球员，真不贵。 （Akul）",
  "缩略图": "//n.sinaimg.cn/finance/page/ent/images/qrcode01.png",
  "正文中的图片": [
    "//n.sinaimg.cn/finance/page/ent/images/qrcode01.png",
    "//n.sinaimg.cn/sports/transform/w650h365/20180101/-kzx-fyqefvw7285493.jpg",
    "http://n.sinaimg.cn/sports/transform/w488h209/20180101/FlyE-fyqefvw7282259.jpg",
    "http://n.sinaimg.cn/sports/transform/w650h433/20180101/HC1H-fyqefvw7285010.jpg"
  ]
}