{
  "url": "http://sports.sina.com.cn/g/laliga/2019-09-26/doc-iicezueu8582456.shtml",
  "标题": "FIFA挪票给梅西？主帅队长抗议:我们都没选梅西！",
  "日期": "2019年09月26日 18:58",
  "正文": "梅西当选国际足联年度足球先生，但在结果公布后的这几天里，国际足联的投票与计票陆续遭到质疑，一些国家足协、国家队主帅和队长公开站出来表示了里面有问题。 根据FIFA的规则，各国国家队的主教练和队长进行投票，梅西力压C罗和范戴克当选。但如今埃及足协、苏丹国家队主帅和尼加拉瓜队长公开表态称，投票过程有问题。 埃及足协表示，埃及国家队主帅加里布与队长阿赫迈德的投票，没有被国际足联统计在内，他们要求获得解释。在FIFA公布的各国投票详情中，没有埃及的这两票，而埃及足协称，他们在8月15日正式递交了选票，此时距离投票截止日还有四天。 另外，苏丹国家队主帅卢加利西奇、尼加拉瓜队长胡安-巴雷拉都在社交媒体上宣称，FIFA的计票结果，和他们实际的投票选择不一样。卢加利西奇称，他投票的第一选择是利物浦的萨拉赫，但FIFA公布的结果中，他这一票却给了梅西。 胡安-巴雷拉也表示，他没有投票给梅西，但在FIFA公布的结果中，却显示他的票给了梅西。“我没有投票给梅西。公布之后我很吃惊，发现自己在投给梅西的队长名单中，到底发生了什么，没有任何解释。” （江岛鸢）",
  "缩略图": "//n.sinaimg.cn/sports/transform/120/w532h388/20190926/bab6-ifaench6801926.jpg",
  "正文中的图片": [
    "//n.sinaimg.cn/sports/transform/120/w532h388/20190926/bab6-ifaench6801926.jpg",
    "//n.sinaimg.cn/sports/transform/60/w506h354/20190926/3caa-ifaench6802615.jpg",
    "//n.sinaimg.cn/sports/transform/142/w543h399/20190926/cc73-ifaench6803815.jpg"
  ]
}