{
  "url": "https://sports.sina.com.cn/g/pl/2022-11-24/doc-imqqsmrp7434847.shtml",
  "标题": "曝贝克汉姆有意合伙收购曼联 已与其他买家进行接触",
  "日期": "2022年11月24日 20:20",
  "正文": " 就在周三晚上，掌控曼联的格雷泽家族的成员之一艾弗拉姆·格雷泽和记者表示，正如之前一天的官方宣告一样，曼联的未来在近期将会被提上议程。“董事开了会，决定考虑不同的策略。我们将看最终采取什么方案，然后看事情最终会发展成什么样。” 几天前传出格雷泽家族将要出售曼联的消息，而之前格雷泽家族一直非常隐晦的表达这件事，拐弯抹角表示可能会以不同形式改变俱乐部，如引入新股东等，而事实上格雷泽家族确实考虑卖盘走人。 那些一直对投资曼联有想法的人现在开始“蠢蠢欲动”了。英国首富拉拉特克里夫爵士早前一直都对曼联感兴趣，特斯拉创始人马斯克也是如此。 不过，当中最引入注目的当属曼联名宿贝克汉姆了。据悉，目前已经拥有迈阿密国际的贝克汉姆早前就接触过相关方面，目前贝克汉姆也表示愿意与俱乐部的潜在买家合作。 如果曼联俱乐部最终被出售，贝克汉姆很可能作为代表之一，联合其他买家一同买下曼联，到时候事情就会变得有意思。 （伊万） ",
  "缩略图": "//n.sinaimg.cn/sports/transform/199/w600h399/20221124/8877-14cc828c81dc5d98d84f2857eef47efd.jpg",
  "正文中的图片": [
    "//n.sinaimg.cn/sports/transform/199/w600h399/20221124/8877-14cc828c81dc5d98d84f2857eef47efd.jpg"
  ]
}