{
  "url": "http://sports.sina.com.cn/g/laliga/2019-02-15/doc-ihqfskcp5352385.shtml",
  "标题": "曝武磊已征服西人内部：他能以6000万欧转会曼联",
  "日期": "2019年02月15日 09:31",
  "正文": "西班牙《国家报》在题为“武磊，西班牙人的中国梦”的最新报道中指出，武磊推动了西班牙人俱乐部的经济发展，但同时也凭借出色的水准和对球队的贡献给人留下深刻印象。不过该报披露，在武磊刚加盟时，曾遭受西班牙人球员的质疑。 “一位中国球员？说真的？”在西班牙人俱乐部官方宣布签下武磊后，西班牙人更衣室里大家都窃窃私语。武磊是亚洲足坛旗帜型的人物，但对西甲球员和球迷来说完全是陌生人。这没什么奇怪的。而且西班牙人俱乐部事实上没有做试验的空间，正因为如此，引进武磊被认为是市场的选择而不是竞技的选项。当时西班牙人队屡战屡败，从排名第二一路跌到接近降级区，球员们盼望的是引进一位能极大提升球队实力的高水准球星。 引进武磊令人感觉意外。“我们很多人都感到非常吃惊。”西班牙人队的更衣室表示。 然而武磊仅仅用了2场比赛，72分钟的上场时间就证明了自己，对巴列卡诺的比赛，他还创造了一个点球。西班牙人球场的看台上出现了中国国旗，他给球队带来了巨大的人气，4000万球迷观看武磊的首秀，他的球衣在中国被销售一空。 “在我们的官方商店里——这是我们唯一能统计数字的地方，已经卖掉了400件武磊的球衣。”西班牙人俱乐部官方商店的一位工作人员表示。没有一位西班牙人的球员能引发如此巨大的热情。 队友们开始称赞武磊。“请注意，他不错，非常好。”队长大卫·洛佩斯点赞武磊。武磊首先让队友注意的是他理解足球的能力，“他稍稍看一下就能抓住要点。他真的很聪明。” 在武磊学习了一些西语后，很快就能运用了。达尔德表示：“传球，传球，每次我拿球，都会冲我这么喊。”头号射手博尔哈·伊格莱西亚指出：“他给我们贡献了很多，他速度快，很具智慧，有进球能力。”主教练鲁比也称赞道：“他的跑动很积极，对手很难追逐他。他很具纵深，这是他能来这里的原因，我们认为他是一位伟大的球员。” 队友维克多·桑切斯也表示：“在训练中，他的头脑里一直都存在对方的球门。他双脚的射门都很出色。要知道，他是过去5个赛季中国的最佳射手。他肯定很强，当然也必须适应。” 西班牙《国家报》表示，中国有个足球梦，武磊则是西班牙人俱乐部的中国梦。“他能以6000万欧元的价格转会曼联。”西班牙人俱乐部内部对武磊的前景非常看好。不过现在唯一可以确定的是，周六客场对瓦伦西亚的比赛，武磊很有可能获得首发位置。（塞尔吉奥）",
  "缩略图": "//n.sinaimg.cn/sports/transform/303/w650h453/20190215/Rmar-htacqwv0701585.jpg",
  "正文中的图片": [
    "//n.sinaimg.cn/sports/transform/303/w650h453/20190215/Rmar-htacqwv0701585.jpg",
    "//n.sinaimg.cn/sports/transform/162/w650h312/20190215/t7aH-htacqwv0705515.jpg",
    "//n.sinaimg.cn/sports/transform/59/w650h209/20190215/nJ2P-htacqwv0715822.png"
  ]
}