{
  "url": "https://sports.sina.com.cn/g/laliga/2020-04-28/doc-iircuyvi0366545.shtml",
  "标题": "曝巴萨出售名将接近达成协议 尤文报价难以拒绝",
  "日期": "2020年04月28日 20:41",
  "正文": "尤文图斯近期盯上了巴萨球员阿图尔，西班牙媒体最新消息称，这笔转会非常接近达成协议。 《世界体育报》透露，尤文想要购买阿图尔，他们已经和巴萨进行了深入的谈判。接触从几周前就开始，尤文图斯给出了巴萨方面难以拒绝的报价。 未来几天将是阿图尔转会谈判的关键时期，如果球员点头的话，巴萨和尤文甚至有希望在联赛重启前达成协议。据悉，尤文愿意把本坦库尔、皮亚尼奇和贝尔纳代斯基加入到交易之中。 尤文主帅萨里很欣赏阿图尔，他希望把这位中场当成未来建队核心。而今阿图尔并不受巴萨主帅塞蒂恩欣赏，巴萨新帅执教了11场比赛，阿图尔只获得了4次首发机会。 （小九）",
  "缩略图": "//n.sinaimg.cn/sports/transform/368/w650h518/20200428/dcb1-isuiksp2476868.png",
  "正文中的图片": [
    "//n.sinaimg.cn/sports/transform/368/w650h518/20200428/dcb1-isuiksp2476868.png"
  ]
}