{
  "url": "http://sports.sina.com.cn/g/laliga/2019-02-02/doc-ihqfskcp2696212.shtml",
  "标题": "武磊首次入选西班牙人大名单 明晚或上演西甲首秀",
  "日期": "2019年02月02日 20:39",
  "正文": "北京时间明晚19点，西班牙人将客场挑战比利亚雷亚尔。中国球员武磊在1月28日转会西班牙人之后，首次入选球队大名单，明晚有望上演西甲首秀。 西班牙人大名单： 门将：1-罗伯托、13-迭戈-洛佩斯； 后卫：8-罗萨莱斯、12-迪达克、16-哈维-洛佩斯、22-埃尔莫索、27-尤易斯、28-佩多萨； 中场：4-维克托-桑切斯、10-达德尔、14-梅伦多、18-阿莱士-洛佩斯、23-格拉内罗； 前锋：7-伊格莱西亚斯、9-塞尔希奥-加西亚、11-费雷拉、19-皮亚蒂、20-普阿多、24-武磊 （林登万）",
  "缩略图": "//n.sinaimg.cn/sports/transform/500/w650h650/20190202/vUJt-hsmkfyn8536920.jpg",
  "正文中的图片": [
    "//n.sinaimg.cn/sports/transform/500/w650h650/20190202/vUJt-hsmkfyn8536920.jpg"
  ]
}