{
  "url": "http://sports.sina.com.cn/g/pl/2017-05-25/doc-ifyfqvmh8774994.shtml",
  "标题": "未找到标题",
  "日期": "未找到日期",
  "正文": "",
  "缩略图": "http://s.img.mix.sina.com.cn/auto/resize?img=http%3A%2F%2Fn.sinaimg.cn%2Fsports%2Ftransform%2F20170525%2F5rBY-fyfquym0417255.jpg&size=100_100",
  "正文中的图片": [
    "http://s.img.mix.sina.com.cn/auto/resize?img=http%3A%2F%2Fn.sinaimg.cn%2Fsports%2Ftransform%2F20170525%2F5rBY-fyfquym0417255.jpg&size=100_100",
    "http://s.img.mix.sina.com.cn/auto/resize?img=http%3A%2F%2Fn.sinaimg.cn%2Fsports%2Ftransform%2F20170525%2F5-Wd-fyfquym0419046.jpg&size=100_100",
    "http://s.img.mix.sina.com.cn/auto/resize?img=http%3A%2F%2Fn.sinaimg.cn%2Fsports%2Ftransform%2F20170525%2FQrkn-fyfkzht0785078.jpg&size=100_100",
    "http://s.img.mix.sina.com.cn/auto/resize?img=http%3A%2F%2Fn.sinaimg.cn%2Fsports%2Ftransform%2F20170525%2FvVu--fyfkzht0781509.jpg&size=100_100",
    "http://s.img.mix.sina.com.cn/auto/resize?img=http%3A%2F%2Fn.sinaimg.cn%2Fsports%2Ftransform%2F20170525%2FO_K9-fyfquww8430077.jpg&size=100_100",
    "http://s.img.mix.sina.com.cn/auto/resize?img=http%3A%2F%2Fn.sinaimg.cn%2Fsports%2Ftransform%2F20170525%2Fod12-fyfquym0418977.jpg&size=100_100",
    "http://s.img.mix.sina.com.cn/auto/resize?img=http%3A%2F%2Fn.sinaimg.cn%2Fsports%2Ftransform%2F20170525%2Fe75r-fyfkzht0783310.jpg&size=100_100",
    "http://s.img.mix.sina.com.cn/auto/resize?img=http%3A%2F%2Fn.sinaimg.cn%2Fsports%2Ftransform%2F20170525%2Fq8Gk-fyfquxv2977104.jpg&size=100_100",
    "http://n.sinaimg.cn/sports/transform/20170525/uNc5-fyfquww8432624.jpg",
    "http://n.sinaimg.cn/sports/transform/20170525/vKj7-fyfkzht0785461.jpg",
    "http://n.sinaimg.cn/sports/transform/20170525/PEpm-fyfquym0418994.gif",
    "http://n.sinaimg.cn/sports/transform/20170525/XTdD-fyfquym0448984.gif",
    "http://n.sinaimg.cn/sports/transform/20170525/zj14-fyfquww8432256.gif",
    "http://n.sinaimg.cn/sports/transform/20170525/LdS7-fyfquww8430872.gif",
    "http://n.sinaimg.cn/sports/transform/20170525/GM_1-fyfquxv2979002.jpg",
    "http://n.sinaimg.cn/sports/transform/20170525/Zo7O-fyfkzht0783762.jpg",
    "http://n.sinaimg.cn/sports/transform/20170525/-Jzt-fyfkzht0784636.gif",
    "http://n.sinaimg.cn/sports/transform/20170525/6L8j-fyfquww8432301.jpg",
    "http://n.sinaimg.cn/sports/transform/20170525/EbtI-fyfquym0419052.jpg",
    "http://n.sinaimg.cn/sports/transform/20170525/CaDl-fyfquww8432559.jpg",
    "http://n.sinaimg.cn/sports/transform/20170525/OHoc-fyfquxv2980694.jpg",
    "http://n.sinaimg.cn/sports/5b976204/20160127/code_wb.png"
  ]
}