{
  "url": "https://sports.sina.com.cn/g/laliga/2021-07-06/doc-ikqcfnca5165022.shtml",
  "标题": "法国两将道歉被指没诚意  日本球迷：别再来亚洲了",
  "日期": "2021年07月06日 07:29",
  "正文": "在一段2年前的视频被曝光后，格列兹曼和登贝莱都为涉嫌歧视日本人表示了道歉。2019年日本行期间，日本工作人员在酒店为他们维修游戏机，他们却表示这些人很丑陋，还说不知道他们说什么鸟语。现在，格列兹曼表示道歉，表示自己从不歧视谁，有些人想抹黑他。登贝莱也表示，自己平时和朋友都这么说话，没特别针对哪个种群。 不过，社交网站上，很多人认为两人的道歉没有诚意。有球迷写道“这不是道歉，这只是登贝莱苍白的努力。登贝莱的道歉可以理解为：我在世界上任何地方都是混蛋，不仅仅在日本。” “这是什么狗屎道歉？登贝莱只是想说，我歧视任何亚洲人，不管他们来自哪里。” 有日本球迷表示：“不要再说日本朋友了。我们不认为你们是我们的朋友。我们认为这不是道歉，只是找借口。别再到亚洲来了！” （伊万） ",
  "缩略图": "//n.sinaimg.cn/sports/transform/215/w650h365/20210706/80c1-ksmehzs7233337.jpg",
  "正文中的图片": [
    "//n.sinaimg.cn/sports/transform/215/w650h365/20210706/80c1-ksmehzs7233337.jpg"
  ]
}