{
  "url": "https://news.zhibo8.com/zuqiu/2024-01-04/65964d2628f6enative.htm",
  "标题": "记者：科雷尔加盟摩纳哥今天敲定，租借费50万欧+买断费1150万欧",
  "日期": "2024-01-04",
  "正文": " 直播吧1月4日讯 据德国天空体育记者Florian Plettenberg消息，科雷尔加盟摩纳哥的交易今天敲定。 记者Florian Plettenberg表示，如果没有任何问题，科雷尔可能会在今天前往摩纳哥敲定交易，这是一笔几乎完成的交易。6个月的租借协议包含1150万欧买断条款，转化为强制买断的条款很容易实现，第一份合同过去1-2天交换，租借费用50万欧元。 科雷尔现年27岁，是一位德国后卫， 2022年以1200万欧转会费从巴黎加盟西汉姆，他本赛季各项赛事仅为西汉姆出战12次，其中英超赛场登场4次。 （Luca）",
  "缩略图": "//tu.duoduocdn.com/uploads/day_221128/6383c43ebaa82_watermark.jpg",
  "正文中的图片": [
    "//tu.duoduocdn.com/uploads/day_221128/6383c43ebaa82_watermark.jpg"
  ]
}