{
  "url": "https://news.zhibo8.com/zuqiu/2024-01-02/659345fc04774native.htm",
  "标题": "近7个赛季英超单场射门纪录前四均由红军创造，本场34次并列第三",
  "日期": "2024-01-02",
  "正文": " 直播吧1月2日讯 在本轮英超利物浦4-2击败纽卡的比赛中，红军狂轰34次射门。 据统计，英超近7个赛季只有4次出现有球队单场射门次数至少达到34次，且全部是红军创造的，以下为具体情况： 2018年12月 利物浦vs曼联 36次 2017年9月 利物浦vs伯恩利 35次 2023年12月 利物浦vs曼联 34次 2024年1月2日 利物浦vs纽卡 34次 （陈皮不是橙）",
  "缩略图": "//tu.duoduocdn.com/uploads/day_220420/625f3eb8d2cd1_watermark.jpg",
  "正文中的图片": [
    "//tu.duoduocdn.com/uploads/day_220420/625f3eb8d2cd1_watermark.jpg"
  ]
}