{
  "url": "https://news.zhibo8.com/zuqiu/2024-01-05/6597cdb5d59fcnative.htm",
  "标题": "意媒：如果囧叔赛季结束后离任，尤文优先考虑请博洛尼亚主帅莫塔",
  "日期": "2024-01-05",
  "正文": " 直播吧1月5日讯 据全市场报道称，如果阿莱格里在赛季结束后离任，尤文的首选是聘请博洛尼亚主帅莫塔。 阿莱格里率领的尤文图斯在本赛季的战绩非常出色，但是他仍然可能会在赛季结束后提前离开尤文。 尤文为此已经开始未雨绸缪，不希望在阿莱格里突然离开的情况下措手不及，总监琼托利希望能够聘请博洛尼亚主帅莫塔。 莫塔率领的博洛尼亚正在竞争欧冠资格，他深受尤文总监琼托利的欢迎，被认为是能够带领尤文年轻球员开启一段新的胜利之旅的理想教练，本赛季的尤文已经有许多年轻球员崭露头角。 不过这很大程度取决于阿莱格里的想法，他与尤文目前仍然还有一年的合同在身。 （冰糖炖雪梨）",
  "缩略图": "//tu.duoduocdn.com/uploads/day_230105/63b5c917092b8_watermark.jpg",
  "正文中的图片": [
    "//tu.duoduocdn.com/uploads/day_230105/63b5c917092b8_watermark.jpg"
  ]
}