{
  "url": "https://news.zhibo8.com/zuqiu/2024-01-07/659a54c019cbfnative.htm",
  "标题": "斯基拉：热刺可选择1800万欧买断维尔纳，若买断双方将签约4年",
  "日期": "2024-01-07",
  "正文": " 直播吧1月7日讯 据意大利记者斯基拉透露，热刺租借维尔纳的协议中包含1800万欧选择买断条款，买断后双方将签约4年。 斯基拉指出，莱比锡前锋维尔纳租借加盟热刺的交易已经完成，租借期限为6个月，租借协议中包含1800万欧的选择买断条款。如果热刺今夏买断维尔纳，双方将签下一份为期4年的合同。 维尔纳本赛季至今为莱比锡出战14场比赛，贡献2粒进球和1次助攻，出场时间386分钟。 （木子）",
  "缩略图": "//tu.duoduocdn.com/uploads/day_221030/635e23509dd69_watermark.jpg",
  "正文中的图片": [
    "//tu.duoduocdn.com/uploads/day_221030/635e23509dd69_watermark.jpg"
  ]
}