{
  "url": "https://news.zhibo8.com/zuqiu/2024-01-11/659f0a2b32c66native.htm",
  "标题": "法媒：米兰双雄和尤文对梅迪纳感兴趣，朗斯不愿在一月放球员离开",
  "日期": "2024-01-11",
  "正文": " 直播吧1月11日讯 据法国媒体Foot Mercato报道，AC米兰、国际米兰和尤文图斯对朗斯中卫梅迪纳感兴趣。 另外据报道，有英超球队也将加入签约梅迪纳的竞争。值得注意的是，朗斯不愿意在一月份放这名主力后卫离队。 朗斯打算延长梅迪纳的合同，球员的现有合同将在2026年6月到期。自2020年以来，梅迪纳一直效力于朗斯，本赛季他各项赛事出战22场比赛，打进1球送出2次助攻。 现年24岁的梅迪纳为阿根廷国家队出战3场比赛，德转对其身价估值为2200万欧元。 （马东宇）",
  "缩略图": "//tu.duoduocdn.com/uploads/day_210119/600680f916d8e.jpg",
  "正文中的图片": [
    "//tu.duoduocdn.com/uploads/day_210119/600680f916d8e.jpg"
  ]
}