{
  "url": "https://news.zhibo8.com/zuqiu/2024-01-07/659abd3a280d1native.htm",
  "标题": "北青：新年伊始已有8支中超球队换帅且均为洋帅，仅3队任用土帅",
  "日期": "2024-01-07",
  "正文": " 直播吧1月7日讯 今日，《北青体育》发文谈到了中超各队的选帅情况，该媒体表示在今日河南队官宣韩国教练南基一上任后，新年伊始已有8支中超球队进行换帅，且均为外国教练，中超16支俱乐部只有3支由本土教练带队。 该媒体写道：“中超联赛经历过去一个赛季的‘复苏’后渐渐回归职业足球本色，但在巨大的生存危机与竞争压力下，绝大多数中超俱乐部不得不寻求变化来改善境遇。尽管换帅成因各异，但目的只有两类—要么健康‘活’下去，要么‘活’得更好些。” “俱乐部准入结果还未通过公示期，已有8家实现了换帅。值得关注的是，他们选用的新帅全部为洋帅。对于这样一个变化，一位资深足球经纪人分析称，中超联赛在经过2020至2022年3个特殊且困难的赛季后，于上赛季重回正常轨道。在本土联赛外援引进恢复常态后，外籍教练员的引进也重新活跃起来。尽管随着‘金元退潮’，类似里皮、斯科拉里这样的国际名帅短期内很难重现于中国职业足坛，外教的‘段位’相应降低了不少，但联赛各集团的竞争激烈程度并没有打折，换洋帅不得不考虑具体操作的性价比。” “据透露，中超各队洋帅身价最高的是崔康熙，他的团队打包年薪在400万美元左右，其次是海港的穆斯卡特和申花的斯卢茨基，约在200万至300万美元之间，其他俱乐部有的在100万美元上下，低的甚至仅有20万至30万美元。相对来说，常年处于联赛竞争第一集团的俱乐部会选用相对知名、价高的外教，而中下游俱乐部在选用外教方面则倾向于追求价格实惠。不过无论高价还是低价，各俱乐部在签约问题上都格外谨慎。此外，追求新帅性价比还体现在目标方向的选择，比如在上文提到的8名新帅中，有6人有执教J联赛、K联赛的经历，他们更加熟悉亚洲足球，也更容易在中超执教岗位上更快上手。” “目前中超16支球队仅剩3支由本土教练员领军。他们分别是沧州雄狮主帅肇俊哲、长春亚泰主帅陈洋和天津津门虎主帅于根伟。他们能够留任，很大程度上得益于上赛季率队的战绩令投资人感到满意，但他们也可能更容易充当俱乐部战绩不理想的‘背锅侠’，因为相较于拿下外教，炒掉本土教练的损失和难度要小很多，同时土帅也往往被习惯性请来当‘救火侠’、过渡主帅。” “从往年的实际情况看，在漫长的一个赛季里，相当一部分球队的帅位都不会一成不变。2024年中超联赛的换帅大戏未完待续。” （Jaden）",
  "缩略图": "//tu.duoduocdn.com/uploads/day_240107/202401071644158004.jpg",
  "正文中的图片": [
    "//tu.duoduocdn.com/uploads/day_240107/202401071644158004.jpg"
  ]
}